smartcontrol/__inti__.py
smartcontrol/calendar.py
smartcontrol/clock.py
smartcontrol-0.1.12.dist-info/LICENSE
smartcontrol-0.1.12.dist-info/METADATA
smartcontrol-0.1.12.dist-info/WHEEL
smartcontrol-0.1.12.dist-info/top_level.txt
smartcontrol-0.1.12.dist-info/RECORD
