Metadata-Version: 2.1
Name: smartcontrol
Version: 0.1.12
Summary: Useful tools to make an automated actions script 
Home-page: https://github.com/badre2dine/smartcontrol
Download-URL: https://pypi.org/project/smartcontrol/
Author: Badreddine bencherki
Author-email: badrbencherki@gmail.com
License: MIT
Keywords: bot,control,clock,timer
Platform: unix
Platform: linux
Platform: osx
Platform: cygwin
Platform: win32
Classifier: Programming Language :: Python :: 3
Classifier: Programming Language :: Python :: 3 :: Only
Classifier: Programming Language :: Python :: 3.6
Classifier: Programming Language :: Python :: 3.7
Classifier: Programming Language :: Python :: 3.8
Classifier: Programming Language :: Python :: 3.9
Requires-Python: >=3.6
License-File: LICENSE
Provides-Extra: testing
Requires-Dist: pytest (>=6.0) ; extra == 'testing'
Requires-Dist: pytest-cov (>=2.0) ; extra == 'testing'
Requires-Dist: mypy (>=0.910) ; extra == 'testing'
Requires-Dist: flake8 (>=3.9) ; extra == 'testing'
Requires-Dist: tox (>=3.24) ; extra == 'testing'
